tnbsclean/__init__.py
tnbsclean/tnbs_clean_module.py
tnbsclean-1.20.dist-info/METADATA
tnbsclean-1.20.dist-info/WHEEL
tnbsclean-1.20.dist-info/top_level.txt
tnbsclean-1.20.dist-info/RECORD
