Metadata-Version: 2.4
Name: tnbsclean
Version: 1.20
License: MIT
Classifier: License :: OSI Approved :: MIT License
Requires-Dist: numpy
Requires-Dist: matplotlib
Requires-Dist: mne
Dynamic: classifier
Dynamic: description
Dynamic: description-content-type
Dynamic: license
Dynamic: requires-dist
